hat/aio/__init__.py
hat/aio/misc.py
hat/aio/group.py
hat/aio/executor.py
hat/aio/queue.py
hat/aio/wait.py
hat_aio-0.7.12.dist-info/LICENSE
hat_aio-0.7.12.dist-info/METADATA
hat_aio-0.7.12.dist-info/WHEEL
hat_aio-0.7.12.dist-info/RECORD
