Metadata-Version: 2.1
Name: hat-aio
Version: 0.7.12
Summary: Hat async utility library
License: Apache-2.0
Classifier: Programming Language :: Python :: 3
Classifier: License :: OSI Approved :: Apache Software License
Provides-Extra: dev
Requires-Dist: hat-doit ~=0.16.2; extra == 'dev'
Requires-Python: >=3.10
Project-URL: Homepage, http://hat-open.com
Project-URL: Repository, https://github.com/hat-open/hat-aio.git
Project-URL: Documentation, http://hat-aio.hat-open.com
